datascav_switch-1.1.0.dist-info/licenses/LICENSE
scav_switch/__init__.py
scav_switch/converters/__init__.py
scav_switch/converters/audio/__init__.py
scav_switch/converters/pdf/__init__.py
scav_switch/converters/pdf/common.py
scav_switch/converters/pdf/exceptions.py
scav_switch/converters/pdf/to_markdown.py
scav_switch/converters/video/__init__.py
scav_switch/utils/__init__.py
datascav_switch-1.1.0.dist-info/METADATA
datascav_switch-1.1.0.dist-info/WHEEL
datascav_switch-1.1.0.dist-info/top_level.txt
datascav_switch-1.1.0.dist-info/RECORD
